{
  "event_id": "019d2030-9f8c-7442-ae60-14a2a5744cf9",
  "occurred_at": "2026-03-24T14:12:30.732385Z",
  "type": "idx.knot_head",
  "data": {
    "deferred_from_state": null,
    "gate": {
      "owner_kind": "agent"
    },
    "invariants": [],
    "knot_id": "loom-72de",
    "profile_id": "autopilot_with_pr",
    "state": "lease_ready",
    "terminal": false,
    "title": "Lease: foolery:terminal_manager_take:term-1774360126276-1hrla0",
    "type": "lease",
    "updated_at": "2026-03-24T14:12:30.732385Z",
    "workflow_id": "compatibility"
  }
}
