{
  "event_id": "019d2030-c0fa-7be0-bcfa-d04c0b4f902f",
  "occurred_at": "2026-03-24T14:12:39.290265Z",
  "type": "idx.knot_head",
  "data": {
    "deferred_from_state": null,
    "gate": {
      "owner_kind": "agent"
    },
    "invariants": [],
    "knot_id": "loom-72de",
    "profile_id": "autopilot_with_pr",
    "state": "lease_active",
    "terminal": false,
    "title": "Lease: foolery:terminal_manager_take:term-1774360126276-1hrla0",
    "type": "lease",
    "updated_at": "2026-03-24T14:12:39.290265Z",
    "workflow_id": "compatibility"
  }
}
