{
  "event_id": "019d10a3-368b-7c02-a533-6f996adb7030",
  "occurred_at": "2026-03-21T13:43:45.029952Z",
  "type": "idx.knot_head",
  "data": {
    "deferred_from_state": null,
    "gate": {
      "owner_kind": "agent"
    },
    "invariants": [],
    "knot_id": "loom-0455",
    "profile_id": "autopilot_no_planning",
    "state": "shipment",
    "terminal": false,
    "title": "loom templates list: align description text",
    "type": "work",
    "updated_at": "2026-03-21T13:43:45.029952Z",
    "workflow_id": "compatibility"
  }
}
